ecraspay/__init__.py
ecraspay/base.py
ecraspay/exceptions.py
ecraspay/https_status_codes.py
ecraspay/modules/__init__.py
ecraspay/modules/bank_transfer.py
ecraspay/modules/card.py
ecraspay/modules/checkout.py
ecraspay/modules/transaction.py
ecraspay/modules/ussd.py
ecraspay/utilities/__init__.py
ecraspay/utilities/card.py
ecraspay/utilities/web.py
tests/__init__.py
tests/test_base.py
tests/test_checkout.py
ecraspay_py-0.1.1.dist-info/LICENSE
ecraspay_py-0.1.1.dist-info/METADATA
ecraspay_py-0.1.1.dist-info/WHEEL
ecraspay_py-0.1.1.dist-info/top_level.txt
ecraspay_py-0.1.1.dist-info/RECORD
