Metadata-Version: 2.1
Name: ecraspay-py
Version: 0.1.1
Summary: A Python wrapper for the ECRAS API.
Home-page: http://github.com/thelimeskies/ecraspay-sdk/src/python
Author: Asikhalaye Samuel
Author-email: samuelasikhalaye@gmail.com
Classifier: Programming Language :: Python :: 3
Classifier: License :: OSI Approved :: MIT License
Classifier: Operating System :: OS Independent
Requires-Python: >=3.6
License-File: LICENSE
Requires-Dist: requests>=2.32.3
Requires-Dist: pycryptodome>=3.11.0
